pyats/easypy/__init__.py
pyats/easypy/base.cpython-39-x86_64-linux-gnu.so
pyats/easypy/commands.cpython-39-x86_64-linux-gnu.so
pyats/easypy/common_funcs.cpython-39-x86_64-linux-gnu.so
pyats/easypy/email.cpython-39-x86_64-linux-gnu.so
pyats/easypy/job.cpython-39-x86_64-linux-gnu.so
pyats/easypy/main.cpython-39-x86_64-linux-gnu.so
pyats/easypy/tasks.cpython-39-x86_64-linux-gnu.so
pyats/easypy/utils.cpython-39-x86_64-linux-gnu.so
pyats/easypy/config/__init__.py
pyats/easypy/config/defaults.cpython-39-x86_64-linux-gnu.so
pyats/easypy/config/loader.cpython-39-x86_64-linux-gnu.so
pyats/easypy/config/manager.cpython-39-x86_64-linux-gnu.so
pyats/easypy/config/schema.cpython-39-x86_64-linux-gnu.so
pyats/easypy/manifest/__init__.py
pyats/easypy/manifest/system.cpython-39-x86_64-linux-gnu.so
pyats/easypy/manifest/virtualenv.cpython-39-x86_64-linux-gnu.so
pyats/easypy/plugins/__init__.py
pyats/easypy/plugins/bases.cpython-39-x86_64-linux-gnu.so
pyats/easypy/plugins/debug.cpython-39-x86_64-linux-gnu.so
pyats/easypy/plugins/htmllogs.cpython-39-x86_64-linux-gnu.so
pyats/easypy/plugins/kleenex.cpython-39-x86_64-linux-gnu.so
pyats/easypy/plugins/logs.cpython-39-x86_64-linux-gnu.so
pyats/easypy/plugins/manager.cpython-39-x86_64-linux-gnu.so
pyats/easypy/plugins/replay.cpython-39-x86_64-linux-gnu.so
pyats/easypy/plugins/rerun.cpython-39-x86_64-linux-gnu.so
pyats/easypy/plugins/retry.cpython-39-x86_64-linux-gnu.so
pyats/easypy/plugins/runinfo.cpython-39-x86_64-linux-gnu.so
pyats/easypy/plugins/stages.cpython-39-x86_64-linux-gnu.so
pyats/easypy/plugins/testbed.cpython-39-x86_64-linux-gnu.so
pyats/easypy/plugins/tips.cpython-39-x86_64-linux-gnu.so
pyats/easypy/plugins/xunit.cpython-39-x86_64-linux-gnu.so
pyats/easypy/reporter/__init__.py
pyats/easypy/reporter/ae.cpython-39-x86_64-linux-gnu.so
pyats/easypy/reporter/base.cpython-39-x86_64-linux-gnu.so
pyats/easypy/reporter/context.cpython-39-x86_64-linux-gnu.so
pyats/easypy/runinfo/__init__.py
pyats.easypy-25.9.dist-info/METADATA
pyats.easypy-25.9.dist-info/WHEEL
pyats.easypy-25.9.dist-info/entry_points.txt
pyats.easypy-25.9.dist-info/top_level.txt
pyats.easypy-25.9.dist-info/RECORD
